luminarycloud/__init__.py
luminarycloud/_feature_flag.py
luminarycloud/_patch.py
luminarycloud/_version.py
luminarycloud/_wrapper.py
luminarycloud/exceptions.py
luminarycloud/feature_modification.py
luminarycloud/geometry.py
luminarycloud/geometry_version.py
luminarycloud/mesh.py
luminarycloud/named_variable_set.py
luminarycloud/project.py
luminarycloud/reference_values.py
luminarycloud/simulation.py
luminarycloud/simulation_param.py
luminarycloud/simulation_queue.py
luminarycloud/simulation_template.py
luminarycloud/solution.py
luminarycloud/tables.py
luminarycloud/tag.py
luminarycloud/volume_selection.py
luminarycloud/workflow_utils.py
luminarycloud/_auth/__init__.py
luminarycloud/_auth/auth.py
luminarycloud/_auth/callback_listener.py
luminarycloud/_auth/config.py
luminarycloud/_auth/credentials_store.py
luminarycloud/_auth/exceptions.py
luminarycloud/_auth/util.py
luminarycloud/_client/__init__.py
luminarycloud/_client/authentication_plugin.py
luminarycloud/_client/client.py
luminarycloud/_client/config.py
luminarycloud/_client/http_client.py
luminarycloud/_client/logging_interceptor.py
luminarycloud/_client/retry_interceptor.py
luminarycloud/_client/rpc_error.py
luminarycloud/_client/tracing.py
luminarycloud/_helpers/__init__.py
luminarycloud/_helpers/_code_representation.py
luminarycloud/_helpers/_create_geometry.py
luminarycloud/_helpers/_create_simulation.py
luminarycloud/_helpers/_entity_identifier.py
luminarycloud/_helpers/_get_project_id.py
luminarycloud/_helpers/_inference_jobs.py
luminarycloud/_helpers/_parse_iso_datetime.py
luminarycloud/_helpers/_simulation_params_from_json.py
luminarycloud/_helpers/_timestamp_to_datetime.py
luminarycloud/_helpers/_upload_mesh.py
luminarycloud/_helpers/_upload_table.py
luminarycloud/_helpers/_wait_for_mesh.py
luminarycloud/_helpers/_wait_for_simulation.py
luminarycloud/_helpers/cond.py
luminarycloud/_helpers/defaults.py
luminarycloud/_helpers/download.py
luminarycloud/_helpers/file_chunk_stream.py
luminarycloud-0.22.3.dist-info/METADATA
luminarycloud-0.22.3.dist-info/WHEEL
luminarycloud-0.22.3.dist-info/RECORD
