Metadata-Version: 2.4
Name: luminarycloud
Version: 0.22.3
Summary: Luminary Cloud SDK
Project-URL: Homepage, https://www.luminarycloud.com/
Project-URL: Documentation, https://app.luminarycloud.com/docs/api/
Author-email: "Luminary Cloud Inc." <support@luminarycloud.com>
Keywords: Luminary Cloud,SDK
Requires-Python: >=3.10
Requires-Dist: google-crc32c~=1.7
Requires-Dist: googleapis-common-protos~=1.70
Requires-Dist: grpcio-status~=1.65
Requires-Dist: grpcio-tools~=1.65
Requires-Dist: grpcio~=1.65
Requires-Dist: importlib-metadata~=8.7
Requires-Dist: opentelemetry-api~=1.25
Requires-Dist: opentelemetry-exporter-otlp-proto-common~=1.25
Requires-Dist: opentelemetry-exporter-otlp-proto-http~=1.25
Requires-Dist: opentelemetry-instrumentation-grpc~=0.55b1
Requires-Dist: opentelemetry-instrumentation~=0.55b1
Requires-Dist: opentelemetry-proto~=1.25
Requires-Dist: opentelemetry-sdk~=1.25
Requires-Dist: opentelemetry-semantic-conventions~=0.55b1
Requires-Dist: protobuf~=5.29
Requires-Dist: pyjwt~=2.10
Requires-Dist: python-dotenv~=1.1
Requires-Dist: pyyaml~=6.0
Requires-Dist: requests~=2.32
Requires-Dist: waitress~=3.0
Requires-Dist: werkzeug~=3.1
Requires-Dist: zstandard~=0.23
Provides-Extra: jupyter
Requires-Dist: luminarycloud-jupyter; extra == 'jupyter'
